LICENSE
MANIFEST.in
README.md
__init__.py
__main__.py
generator.py
requirements.txt
setup.py
tests.jinja2
./LICENSE
./README.md
./__init__.py
./__main__.py
./generator.py
./requirements.txt
./tests.jinja2
./tests.py
django_apiblueprint_tests.egg-info/PKG-INFO
django_apiblueprint_tests.egg-info/SOURCES.txt
django_apiblueprint_tests.egg-info/dependency_links.txt
django_apiblueprint_tests.egg-info/requires.txt
django_apiblueprint_tests.egg-info/top_level.txt