Metadata-Version: 1.1
Name: django-apiblueprint-tests
Version: 0.1.0
Summary: Django REST framework tests generator which is based on API Blueprint (https://apiblueprint.org/) documents.
Home-page: https://github.com/vmarkovtsev/django-apiblueprint-tests
Author: Vadim Markovtsev
Author-email: gmarkhor@gmail.com
License: New BSD
Download-URL: https://github.com/vmarkovtsev/django-apiblueprint-tests
Keywords: blueprint,apiblueprint
Platform: UNKNOWN
Classifier: Development Status :: 4 - Beta
Classifier: Environment :: Console
Classifier: Intended Audience :: Developers
Classifier: License :: OSI Approved :: BSD License
Classifier: Operating System :: POSIX
Classifier: Programming Language :: Python :: 2.7
Classifier: Programming Language :: Python :: 3.2
Classifier: Programming Language :: Python :: 3.3
Classifier: Programming Language :: Python :: 3.4
Classifier: Topic :: Software Development :: Libraries
